rna_tools/BlastPDB.py
rna_tools/RfamSearch.py
rna_tools/SecondaryStructure.py
rna_tools/Seq.py
rna_tools/__init__.py
rna_tools/_version.py
rna_tools/pytest.ini
rna_tools/rchie.png
rna_tools/rna_calc_fenergy.py
rna_tools/rna_dot2ct.py
rna_tools/rna_pdb_inspect.py
rna_tools/rna_pdb_replace.py
rna_tools/rna_pdb_tools.py
rna_tools/rna_secondary_structure_prediction.py
rna_tools/rna_simrnaweb_download_job.py
rna_tools/rna_standardize.py
rna_tools/rna_tools_config.py
rna_tools/rna_tools_lib.py
rna_tools/rna_tools_test_all.py
rna_tools/rna_torsions.py
rna_tools/shell_rc.sh
rna_tools/stats.py
rna_tools/test.sh
rna_tools/update_readme.py
rna_tools/data/260c8ff6-f24e-4eff-9760-1831407fc770_ALL_thrs5.30A_clust01-000001_AA.pdb
rna_tools/data/A.pdb
rna_tools/data/ACGU.pdb
rna_tools/data/C.pdb
rna_tools/data/G.pdb
rna_tools/data/PO3_inner.pdb
rna_tools/data/U.pdb
rna_tools/data/o2prim.pdb
rna_tools/data/op4.pdb
rna_tools/data/pdb_ids.txt
rna_tools/data/rna_pdb_errors.csv
rna_tools/data/shape.txt
rna_tools/tests/test_eval.py
rna_tools/tests/test_rna_ss_pred.sh
rna_tools/tests/test_rnafold.py
rna_tools/tests/test_seq_cyclefold.py
rna_tools/tests/test_seq_mcfold.py
rna_tools/tests/test_seq_mcfold2.py
rna_tools/tests/test_import_module/rchie.png
rna_tools/tests/test_import_module/test_import_rna_tools.py
rna_tools/tests/test_import_module/test_data/RF00167.stockholm.sto
rna_tools/tools/__init__.py
rna_tools/tools/ClashCalc/.gitignore
rna_tools/tools/ClashCalc/ClashCalc.py
rna_tools/tools/ClashCalc/README.md
rna_tools/tools/ClashCalc/__init__.py
rna_tools/tools/ClashCalc/test_data/no_clash.pdb
rna_tools/tools/ClashCalc/test_data/prot-na_2392.pdb
rna_tools/tools/ClashCalc/test_data/super_clash.pdb
rna_tools/tools/PyMOL4RNA/PyMOL4RNA.py
rna_tools/tools/PyMOL4RNA/PyMOL4Spliceosome.py
rna_tools/tools/PyMOL4RNA/README.md
rna_tools/tools/PyMOL4RNA/Spliceosome_PyMOL-2020.ipynb
rna_tools/tools/PyMOL4RNA/Spliceosome_PyMOL-2022.ipynb
rna_tools/tools/PyMOL4RNA/Spliceosome_PyMOL.csv
rna_tools-3.18.dist-info/LICENSE
rna_tools-3.18.dist-info/METADATA
rna_tools-3.18.dist-info/WHEEL
rna_tools-3.18.dist-info/top_level.txt
rna_tools-3.18.dist-info/RECORD
