Metadata-Version: 2.1
Name: rna-tools
Version: 3.18
Summary: a toolbox to analyze structures and simulations of RNA
Home-page: https://github.com/mmagnus/rna-tools
Author: Marcin Magnus
Author-email: mag_dex@o2.pl
License: GPLv3
License-File: LICENSE
Requires-Dist: numpy
Requires-Dist: biopython
Requires-Dist: progressbar2
Requires-Dist: tqdm
Requires-Dist: csvsort
Requires-Dist: simplejson
Requires-Dist: urllib3
Requires-Dist: wget
Requires-Dist: versioneer
Requires-Dist: configparser
Requires-Dist: icecream
